{
    "members": [
        {
            "name": "Two Jacks Pizza",
            "address": "80 W Center St, Provo, UT 84601",
            "phone": "(801) 377-4747",
            "website": "https://www.twojackspizza.com/",
            "image": "https://github.com/asaltycarebear/wdd231/blob/main/chamber/images/logos/two-jacks.webp?raw=true",
            "membershipLevel": 3,
            "description": "Only the best Pizza in the state.",
            "hours": "11 AM - 10PM",
            "email": "NA"
        },
        {
            "name": "Joe's Burgurs",
            "address": "490 N Freedom Blvd Provo, UT 84601",
            "phone": "(801) 377-5637",
            "website": "NA",
            "image": "https://github.com/asaltycarebear/wdd231/blob/main/chamber/images/logos/joes.webp?raw=true",
            "membershipLevel": 1,
            "description": "Burgers from long past...we miss you.",
            "hours": "11 AM - 10PM",
            "email": "NA"
        },
        {
            "name": "Brick Oven",
            "address": "111 E 800 N, Provo, UT 84606",
            "phone": "(801) 374-8800",
            "website": "https://brickovenrestaurants.com/",
            "image": "https://github.com/asaltycarebear/wdd231/blob/main/chamber/images/logos/brick-oven.webp?raw=true",
            "membershipLevel": 1,
            "description": "Flagship of a pizzeria chain serving all-you-can-eat pasta, soup & salad, plus signature root beer.",
            "hours": "11 AM - 10PM",
            "email": "NA"
        },
        {
            "name": "Lowes Xtreme Air Sports",
            "address": "1111 W 100 S, Provo, UT 84601",
            "phone": "(801) 374-5867",
            "website": "https://www.lowesairsports.com/",
            "image": "https://github.com/asaltycarebear/wdd231/blob/main/chamber/images/logos/lowes.webp?raw=true",
            "membershipLevel": 3,
            "description": "The original trampoline arena in Utah",
            "hours": "11 AM - 10PM",
            "email": "NA"
        },
        {
            "name": "Provo Beach",
            "address": "4801 N University Ave #210, Provo, UT 84604",
            "phone": "(801) 224-5001",
            "website": "https://www.provobeach.com/",
            "image": "https://github.com/asaltycarebear/wdd231/blob/main/chamber/images/logos/provo-beach.webp?raw=true",
            "membershipLevel": 1,
            "description": "Beach day in the mountains",
            "hours": "11 AM - 9PM",
            "email": "NA"
        },
        {
            "name": "BYU Creamery on Ninth",
            "address": "1209 900 E, Provo, UT 84604",
            "phone": "(801) 422-2663",
            "website": "https://dining.byu.edu/creamery-on-ninth",
            "image": "https://github.com/asaltycarebear/wdd231/blob/main/chamber/images/logos/creamery.webp?raw=true",
            "membershipLevel": 2,
            "description": "Ice Cream Flavors​​ From Graham Canyon to Cookies and Cream, from classic Vanilla to Mint Chocolate Chip, the Creameries have it all!",
            "hours": "11 AM - 9PM",
            "email": "NA"
        },
        {
            "name": "Fat Cats Provo",
            "address": "1200 N University Ave, Provo, UT 84604",
            "phone": "(801) 373-1863",
            "website": "https://www.fatcatsfun.com/provo",
            "image": "https://github.com/asaltycarebear/wdd231/blob/main/chamber/images/logos/fatcats.webp?raw=true",
            "membershipLevel": 3,
            "description": "FatCats Provo is an entertainment venue offering a variety of activities including bowling, an arcade, and a large food court.",
            "hours": "11 AM - 9PM",
            "email": "NA"
        }
    ]
}